xrtc/__init__.py
xrtc/api/async_context_manager.py
xrtc/api/context_manager.py
xrtc/api/data_models.py
xrtc-0.1.5.dist-info/LICENSE.txt
xrtc-0.1.5.dist-info/METADATA
xrtc-0.1.5.dist-info/WHEEL
xrtc-0.1.5.dist-info/top_level.txt
xrtc-0.1.5.dist-info/RECORD
