Metadata-Version: 2.1
Name: xrtc
Version: 0.1.5
Summary: SDK for XRTC API - the next generation TCP streaming protocol
Home-page: https://xrtc.org
Download-URL: https://github.com/xrtc-org/xrtc-sdk-python
Author: Delta Cygni Labs Ltd
License: Apache-2.0
Requires-Python: >=3.10
License-File: LICENSE.txt
Requires-Dist: python-dotenv (>=0.21.1)
Requires-Dist: pydantic (>=1.10.4)
Requires-Dist: requests (>=2.28.2)
Requires-Dist: aiohttp (>=3.8.3)
Requires-Dist: certifi (>=2022.12.7)
